library/__init__.py
library/code.py
numenc_pkg-0.0.2.dist-info/LICENSE
numenc_pkg-0.0.2.dist-info/METADATA
numenc_pkg-0.0.2.dist-info/WHEEL
numenc_pkg-0.0.2.dist-info/top_level.txt
numenc_pkg-0.0.2.dist-info/RECORD
